chips/__init__.py
chips/chips.py
chips/fetch.py
chips/plots.py
chips/syn_chips.py
pyCHIPS-0.4.5.dist-info/LICENSE
pyCHIPS-0.4.5.dist-info/METADATA
pyCHIPS-0.4.5.dist-info/WHEEL
pyCHIPS-0.4.5.dist-info/top_level.txt
pyCHIPS-0.4.5.dist-info/RECORD
